pero_indexer/helper.py
pero_indexer/NER/convert_dataset.py
pero_indexer/NER/create_lmdb.py
pero_indexer/NER/dataset.py
pero_indexer/NER/helper.py
pero_indexer/NER/inference.py
pero_indexer/NER/model.py
pero_indexer/NER/sequence_lengths.py
pero_indexer/NER/test.py
pero_indexer/NER/tester.py
pero_indexer/NER/train.py
pero_indexer/NER/trainer.py
pero_indexer/alignment/align_levenshtein.py
pero_indexer/alignment/merge_alignment_annotations.py
pero_indexer/alignment/preprocess.py
pero_indexer/alignment/timeout.py
pero_indexer/library_cards/filter_bib_db.py
pero_indexer/library_cards/index_build_bib.py
pero_indexer/library_cards/matching_cards.py
pero_indexer/library_cards/matching_util.py
pero_indexer-0.1.0.dist-info/METADATA
pero_indexer-0.1.0.dist-info/WHEEL
pero_indexer-0.1.0.dist-info/entry_points.txt
pero_indexer-0.1.0.dist-info/top_level.txt
pero_indexer-0.1.0.dist-info/RECORD
